{
  "data": null,
  "loanDTO": {
    "loanProcessAction": null,
    "loanAccount": {
      "id": 377,
      "version": 121,
      "accountNumber": null,
      "bankId": 1,
      "branchId": 12,
      "partnerCode": "northernarc",
      "loanType": "UNSECURED",
      "processType": "OWN",
      "productType": "EQ",
      "productCode": "UBNA1",
      "urnNo": "2205276093390001",
      "customerId": 172,
      "dob": "1958-10-28",
      "loanAmount": 100000,
      "frequency": "W",
      "tenure": "12",
      "tenureInYears": null,
      "interestRate": 12,
      "closed": false,
      "sbAccountNo": null,
      "loanPurpose1": "Personal Expenses",
      "loanPurpose2": "Medical Expenses",
      "loanPurpose3": "Medical Expenses",
      "loanApplicationDate": "2020-11-22",
      "loanDisbursementDate": null,
      "relation": null,
      "husbandOrFatherFirstName": null,
      "husbandOrFatherMiddleName": null,
      "husbandOrFatherLastName": null,
      "borrowerIlliterate": false,
      "literateWitnessFirstName": null,
      "literateWitnessMiddleName": null,
      "literateWitnessLastName": null,
      "witnessRelationship": null,
      "witnessFirstName": null,
      "witnessMiddleName": null,
      "witnessLastName": null,
      "wmName": "Divya",
      "dscLoanAmount": null,
      "dscOverride": false,
      "dscOverrideRemarks": null,
      "dscIntegrationId": null,
      "applicationStatus": "OPEN",
      "applicationStatusUpdatedOn": null,
      "applicationStatusUpdatedBy": null,
      "applicationFileName": null,
      "loanAmountRequested": 120000,
      "disbursedAmountInPaisa": null,
      "startTime": "2022-11-09T06:11:18Z",
      "endTime": "2022-11-09T06:11:18Z",
      "coBorrowerUrnNo": null,
      "chk1UploadFilePath": null,
      "currentStage": "Completed",
      "pendingApproval": null,
      "numberOfDisbursed": 0,
      "numberOfDisbursements": 1,
      "documentTracking": "PENDING",
      "sanctionDate": "2020-11-22",
      "disbursementFromBankAccountNumber": null,
      "isRestructure": false,
      "originalAccountNumber": null,
      "customerBank": "KARNATAKA BANK LIMITED",
      "customerBranch": "KANAKADASANAGAR",
      "customerBankAccountNumber": "6912937717",
      "customerBankIfscCode": "KARB0000623",
      "applicant": "2205276093390001",
      "coApplicant": null,
      "processingFeeInPaisa": 200000,
      "equatedInstallmentAmount": null,
      "oldAccountNO": null,
      "insuranceFee": null,
      "commercialCibilCharge": 0,
      "securityEmi": null,
      "otherFee": null,
      "portfolioInsuranceUrn": "2205276093390001",
      "portfolioInsurancePremium": 0,
      "processingFeePercentage": 2,
      "securityEmiRequired": "No",
      "fee3": 0,
      "fee4": 0,
      "fee5": 0,
      "portfolioInsurancePremiumCalculated": null,
      "firstRepaymentDate": "2020-12-05",
      "loanClosedBy": null,
      "loanClosedAt": null,
      "securityDepositAllowed": false,
      "processingFeeServiceTax": null,
      "portfolioInsuranceServiceCharge": null,
      "annualizedPercentage": 28.35,
      "portfolioInsuranceServiceTax": null,
      "leadId": null,
      "screeningDate": null,
      "assetAvailableForHypothecation": null,
      "estimatedValueOfAssets": null,
      "frequencyRequested": "Weekly",
      "emiRequested": 0,
      "emiPaymentDateRequested": null,
      "expectedInterestRate": 12,
      "tenureRequested": 12,
      "estimatedDateOfCompletion": null,
      "customerSignDateExpected": null,
      "expectedJobCreation": null,
      "expectedIncrementalIncome": null,
      "expectedInterestSaving": null,
      "maxEmi": 8654.13,
      "expectedProcessingFeePercentage": null,
      "expectedCommercialCibilCharge": null,
      "status": null,
      "rejectReason": "Customer Created Successfully",
      "psychometricCompleted": "N",
      "estimatedEmi": 8461,
      "productCategory": "Personal loan",
      "proposedHires": null,
      "percentageIncreasedIncome": null,
      "percentageInterestSaved": null,
      "expectedPortfolioInsurancePremium": 0,
      "fileNumber": 2260,
      "lastStageChangedAt": "2022-11-09T07:45:17Z",
      "linkedAccountNumber": null,
      "isNpa": null,
      "partnerApprovalStatus": null,
      "partnerRemarks": null,
      "collectionBankName": null,
      "collectionBankBranchName": null,
      "collectionIfscCode": null,
      "collectionAccountNumber": null,
      "collectionAccountType": null,
      "collectionCustomerNameAsInBank": null,
      "collectionPaymentType": null,
      "applicationFileId": null,
      "chk1FileUploadId": null,
      "doCustomerLoanAmount": null,
      "partnerLoanAmount": null,
      "doCustomerProcessingFee": null,
      "partnerProcessingFee": null,
      "scheduleStartDate": null,
      "customerPortfolioInsurancePremium": null,
      "spousePortfolioInsurancePremium": null,
      "insuranceType": null,
      "insuranceRateCode": null,
      "partnerAccountNumber": null,
      "preEmi": 0,
      "loanCycle": 7,
      "gstNumber": null,
      "loanToValue": null,
      "dsaPayout": null,
      "dealIrr": null,
      "valuator": null,
      "verificationStatus": null,
      "verificationReason": null,
      "loanInsurance": null,
      "bcAccount": null,
      "loanCentre": {
        "id": 335,
        "loanId": 377,
        "centreId": 534
      },
      "branchCode": null,
      "maximumStageOrder": 15,
      "payeeName": null,
      "payeeMobileNumber": null,
      "payeeAddress": null,
      "assignedTo": null,
      "payeeRelationToApplicant": null,
      "loanChannels": null,
      "parentLoanAccount": null,
      "actualAmountRequired": null,
      "fundsFromDifferentSources": null,
      "baseLoanAccount": null,
      "isSendBack": null,
      "priority": null,
      "fiRemarks": null,
      "noOfGuarantersRequired": 0,
      "collateral": [],
      "jewelLoanDetails": null,
      "accountUserDefinedFields": {
        "id": 263,
        "version": 24,
        "accountNumber": null,
        "userDefinedFieldValues": {
          "udf16": "pending",
          "udf26": "NACH",
          "udf8": "true",
          "udf10": "true",
          "udf42": "5215491401197214",
          "udf41": "5119463424775197"
        },
        "userDefinedDateFieldValues": {},
        "loanId": 377
      },
      "nominees": [],
      "guarantors": [],
      "ornamentsAppraisals": [],
      "loanDocuments": [
        {
          "id": 87,
          "version": 2,
          "loanId": 377,
          "documentId": "a8b9b26a-c808-4bd3-9918-448d1b77f30b",
          "document": "UB_Agreement",
          "documentStatus": "APPROVED",
          "remarks": null,
          "disbursementId": null,
          "accountNumber": null,
          "rejectReason": null,
          "masterDocument": false,
          "verificationRequired": false,
          "deferralStatus": false,
          "deferralDays": null,
          "stampRequired": false,
          "signRequired": false,
          "signingGroupName": null,
          "stampRequestedAt": null,
          "signRequestedAt": null,
          "stampReceivedAt": null,
          "signReceivedAt": null,
          "signStatus": null,
          "stampStatus": null,
          "udf1": null,
          "udf2": null,
          "udf3": null,
          "udf4": null,
          "udf5": null
        },
        {
          "id": 88,
          "version": 2,
          "loanId": 377,
          "documentId": "e9dbf078-45b4-4abb-a0a7-1ce1a90327fe",
          "document": "SANCTION_LETTER",
          "documentStatus": "APPROVED",
          "remarks": null,
          "disbursementId": null,
          "accountNumber": null,
          "rejectReason": null,
          "masterDocument": false,
          "verificationRequired": false,
          "deferralStatus": false,
          "deferralDays": null,
          "stampRequired": false,
          "signRequired": false,
          "signingGroupName": null,
          "stampRequestedAt": null,
          "signRequestedAt": null,
          "stampReceivedAt": null,
          "signReceivedAt": null,
          "signStatus": null,
          "stampStatus": null,
          "udf1": null,
          "udf2": null,
          "udf3": null,
          "udf4": null,
          "udf5": null
        },
        {
          "id": 89,
          "version": 2,
          "loanId": 377,
          "documentId": "c7a2fa95-bf14-4c20-82e7-d01893877a57",
          "document": "APPLICATION_FORM",
          "documentStatus": "APPROVED",
          "remarks": null,
          "disbursementId": null,
          "accountNumber": null,
          "rejectReason": null,
          "masterDocument": false,
          "verificationRequired": false,
          "deferralStatus": false,
          "deferralDays": null,
          "stampRequired": false,
          "signRequired": false,
          "signingGroupName": null,
          "stampRequestedAt": null,
          "signRequestedAt": null,
          "stampReceivedAt": null,
          "signReceivedAt": null,
          "signStatus": null,
          "stampStatus": null,
          "udf1": null,
          "udf2": null,
          "udf3": null,
          "udf4": null,
          "udf5": null
        },
        {
          "id": 90,
          "version": 2,
          "loanId": 377,
          "documentId": "a8c41e81-b612-42a4-832d-6b50cf1ee6d4",
          "document": "LOAN_AGREEMENT",
          "documentStatus": "APPROVED",
          "remarks": null,
          "disbursementId": null,
          "accountNumber": null,
          "rejectReason": null,
          "masterDocument": false,
          "verificationRequired": false,
          "deferralStatus": false,
          "deferralDays": null,
          "stampRequired": false,
          "signRequired": false,
          "signingGroupName": null,
          "stampRequestedAt": null,
          "signRequestedAt": null,
          "stampReceivedAt": null,
          "signReceivedAt": null,
          "signStatus": null,
          "stampStatus": null,
          "udf1": null,
          "udf2": null,
          "udf3": null,
          "udf4": null,
          "udf5": null
        },
        {
          "id": 91,
          "version": 2,
          "loanId": 377,
          "documentId": "9f5de4dc-b7e5-417f-9dc9-e818c12f48c2",
          "document": "ENACH",
          "documentStatus": "APPROVED",
          "remarks": null,
          "disbursementId": null,
          "accountNumber": null,
          "rejectReason": null,
          "masterDocument": false,
          "verificationRequired": false,
          "deferralStatus": false,
          "deferralDays": null,
          "stampRequired": false,
          "signRequired": false,
          "signingGroupName": null,
          "stampRequestedAt": null,
          "signRequestedAt": null,
          "stampReceivedAt": null,
          "signReceivedAt": null,
          "signStatus": null,
          "stampStatus": null,
          "udf1": null,
          "udf2": null,
          "udf3": null,
          "udf4": null,
          "udf5": null
        }
      ],
      "disbursementSchedules": [
        {
          "id": 188,
          "version": 3,
          "scheduledDisbursementDate": "2020-11-23",
          "actualDisbursementDate": null,
          "disbursementAmount": 100000,
          "disbursedAmount": null,
          "customerSignatureDate": "2020-11-22",
          "currentStage": "ReadyForDisbursement",
          "loanId": 377,
          "disbursementFromBankAccountNumber": null,
          "trancheNumber": "1",
          "customerAccountNumber": "6912937717",
          "ifscCode": "KARB0000623",
          "udf1": null,
          "udf2": null,
          "udf3": null,
          "udf4": null,
          "udf5": null,
          "udfDate1": null,
          "udfDate2": null,
          "udfDate3": null,
          "udfDate4": null,
          "udfDate5": null,
          "accountNumber": null,
          "customerName": null,
          "latitude": null,
          "longitude": null,
          "photoImageId": null,
          "transactionId": null,
          "remarks1": null,
          "remarks2": null,
          "modeOfDisbursement": "NEFT",
          "responseCode": null,
          "tranchCondition": "Advance Paid Receipt",
          "customerBankName": "KARNATAKA BANK LIMITED",
          "customerBankBranchName": "KANAKADASANAGAR",
          "party": "CUSTOMER",
          "customerNameInBank": "ajSBDc;abscaj",
          "referenceNumber": null,
          "referenceDate": null,
          "moratoriumPeriodInDays": null,
          "principalDuePayment": null,
          "normalInterestDuePayment": null,
          "penalInterestDuePayment": null,
          "bookedNotDueNormalInterestPayment": null,
          "bookedNotDuePenalInterestPayment": null,
          "feeAmountPayment": null,
          "fpVerified": false,
          "overrideRequested": false,
          "overrideStatus": null,
          "overrideRequestRemarks": null,
          "overrideCheckerRemarks": null,
          "partnerAccountNumber": null,
          "maximumStageOrder": null,
          "linkedAccountTotalPrincipalDue": null,
          "linkedAccountNormalInterestDue": null,
          "linkedAccountPenalInterestDue": null,
          "linkedAccountTotalFeeDue": null,
          "linkedAccountPreclosureFee": null,
          "linkedAccountSecurityDeposit": null,
          "firstRepaymentDate": null,
          "projectedDisbursementAmount": 97640,
          "netDisbursementAmount": null,
          "scheduleStartDate": null,
          "moratoriumAmount": null,
          "disbursementTransactionType": null,
          "transactionType": null,
          "linkedAccountPayOffAmountWithDue": null,
          "mobilePhone": null,
          "processName": null,
          "guaranteeAmount": null,
          "ignoreBankValidation": null
        }
      ],
      "loanCustomerRelations": [
        {
          "id": 518,
          "version": 0,
          "loanId": 377,
          "urn": "2205276093390001",
          "relation": "Applicant",
          "customerId": 172,
          "relationshipWithApplicant": null,
          "psychometricRequired": null,
          "psychometricCompleted": null,
          "dscId": null,
          "dscLimitInPaisa": null,
          "dscStatus": null,
          "dscOverrideRemarks": null,
          "dscOverrideRequestRemarks": null,
          "dscOverrideRequestFileId": null,
          "customerSnapshotId": null,
          "teleCallingDetailsSnapshotId": null
        }
      ],
      "loanMitigants": [],
      "telecallingDetails": [],
      "vehicleLoanDetails": null,
      "newLoanDemandSchedules": [],
      "loanUtilisationDetail": [],
      "transactionType": "New Loan",
      "schemeCode": null,
      "jlgGroupId": null,
      "jlgGroupMemeberId": null,
      "groupCode": null,
      "groupName": null,
      "numberOfEmi": null,
      "securityEmiOverrideReason": null,
      "expectedDisbursementAmount": null,
      "agentId": null,
      "sendBackReason": null,
      "disbursementTransactionType": null,
      "collectionPriority": null,
      "processingFeeFlatOrPercentage": null,
      "riskCategory": null,
      "derivedInterestRate": null,
      "loanRuleInfo": {
        "id": 4312,
        "version": 1,
        "loanId": 377,
        "ruleId": 185,
        "ruleName": "DocumentVerificationToPendingForPartner",
        "currentStage": "DocumentVerification",
        "toStage": "PendingForPartner",
        "ruleParamValues": null,
        "ruleExpression": "loanAccount.partnerCode == 'northernarc'"
      },
      "tagAccount": null,
      "turnOverMethod": null,
      "leadSource": null,
      "familyId": null,
      "processName": "PersonalLoan",
      "loanAccountAdditional": {
        "id": 12906,
        "version": 0,
        "loanId": 377,
        "ltvPercentage": null,
        "penaltyCondition": null,
        "irr": null,
        "interestRateDescription": null,
        "customerExposureAmount": null,
        "barcodeNumber": "GTP0000000230",
        "dealId": null,
        "colendingAccountNumber": null,
        "colendingBankInterestRate": null,
        "colendingNbfcInterestRate": null,
        "colendingPercentage": null,
        "guaranteeAccountId": null,
        "netIncomeOfBorrower": null,
        "netIncomeOfHousehold": null,
        "creditBureauScore": null,
        "guaranteeAmount": null,
        "maturityDate": null,
        "guaranteeStartDate": null,
        "guaranteeAccountPoolId": null,
        "virtualAccountNumber": null,
        "imdFee": null,
        "imdServiceTax": null,
        "totalImdFee": null,
        "firstLoanForLimit": null,
        "limitId": null,
        "availableCustomerLimit": null,
        "outstandingAmount": null,
        "guarantorLimitId": null,
        "availableGuarantorLimit": null,
        "guarantorOutstandingLimit": null,
        "taggingStatus": null,
        "rfidNumber": null,
        "rfName": null,
        "vendorName": null,
        "remarks": null,
        "accountOpeningDate": null
      },
      "parentLoanAccountsDetails": [],
      "loanInputSchedules": [],
      "disbursementConditions": [],
      "collectionCentreId": null,
      "collectionCentreName": null,
      "leadType": null,
      "fee6": 0,
      "fee7": 0,
      "fee8": 0,
      "fee9": 0,
      "fee10": 0,
      "fee11": 0,
      "fee12": 0,
      "fee13": 0,
      "fee14": 0,
      "fee15": 0,
      "fee16": 0,
      "fee17": 0,
      "fee18": 0,
      "fee19": 0,
      "fee20": 0,
      "orderMarginDetail": null,
      "scoreCalculation": null,
      "totalAmountToBeRepaid": null
    },
    "applicant": null,
    "coApplicants": null,
    "gaurantors": null,
    "enterprise": null,
    "stage": null,
    "remarks": null,
    "currentStage": "Completed"
  },
  "enrollmentDTO": {
    "enrollmentAction": null,
    "customer": {
      "id": 172,
      "version": 21,
      "enrollmentId": "00002705221549532520",
      "urnNo": "2205276093390001",
      "firstName": "RAGHAVENDRA K M",
      "lastName": "awdawdaw",
      "middleName": "",
      "nickName": null,
      "fatherFirstName": "MANI",
      "fatherLastName": "",
      "fatherMiddleName": "",
      "maritalStatus": "MARRIED",
      "citizenOfIndia": null,
      "employmentStatus": null,
      "landLineNo": null,
      "mobilePhone": "9080610417",
      "stdCode": null,
      "dateOfBirth": "1958-10-28",
      "gender": "MALE",
      "dateOfBirthLong": -352791000000,
      "customerCategory": null,
      "title": "false",
      "spouseFirstName": "undefined",
      "spouseMiddleName": "",
      "spouseLastName": "",
      "spouseDateOfBirth": "1991-05-15",
      "caste": null,
      "religion": null,
      "language": "Hindi",
      "exserviceman": null,
      "villageName": "Mahalingapur(Rural)",
      "occupation1": "Deliveries service",
      "occupation2": "Rental Income",
      "occupation3": "Agri Income",
      "occupation4": null,
      "kgfsName": "Head Office",
      "kgfsBankName": "DvaraMoney",
      "kycFurnishedCopyEnclosed": null,
      "doorNo": "NO 713 PV KOIL STREET POONAMALLEE HIGH ROADD AMINJIKARAI CHENNAI TAMIL NADU 600029",
      "street": "hkghvgjlgv",
      "postOffice": "Aminijikarai POST OFFICE",
      "locality": "Mahalingapur(Rural)",
      "district": "BAGALKOT",
      "state": "KARNATAKA",
      "pincode": 587312,
      "mailSameAsResidence": false,
      "mailingDoorNo": "NO 713 PV KOIL STREET POONAMALLEE HIGH ROADD AMINJIKARAI CHENNAI TAMIL NADU 600029",
      "mailingStreet": "hkghvgjlgv",
      "mailingLocality": "Mahalingapur(Rural)",
      "mailingPostoffice": "Aminijikarai POST OFFICE",
      "mailingDistrict": "BAGALKOT",
      "mailingState": "KARNATAKA",
      "mailingPincode": "587312",
      "addressProof": "Aadhar Card",
      "identityProof": "Pan Card",
      "identityProofNo": "BPTPR9431R",
      "panNo": "BPTPR9431R",
      "yearsOfExperience": null,
      "nameOfRo": "Divya",
      "date": "2022-05-27",
      "place": null,
      "addressProofImageId": "7b698aa6-7e7a-4334-9b81-35774a88738f",
      "identityProofImageId": "d286bb02-8557-449c-9013-16f53fff8ea6",
      "verified": false,
      "parentCustomerId": 0,
      "familyEnrollmentId": null,
      "latestPanStatus": null,
      "latestPanStatusUpdatedOn": null,
      "offlineUploadedOn": null,
      "panCardImageId": null,
      "customerStatus": "ACTIVE",
      "mobileEnrollment": null,
      "mobileEnrollmentId": null,
      "urnGeneratedDate": "2022-05-27T10:19:54Z",
      "bcCustId": "IR0000177",
      "inviteId": null,
      "latitude": null,
      "longitude": null,
      "altitude": null,
      "gpsCaptureDate": null,
      "enrolledAs": "CUSTOMER",
      "blocked": false,
      "blockStatusChangedBy": null,
      "blockStatusChangedAt": null,
      "cifNo": null,
      "sanctionListBlocked": false,
      "addressProofIssueDate": null,
      "addressProofValidUptoDate": null,
      "idProofIssueDate": null,
      "idProofValidUptoDate": null,
      "ageProof": null,
      "ageProofImageId": null,
      "aadhaarNo": "492368691011",
      "eidNumber": null,
      "eidDate": null,
      "addressRationCardType": null,
      "identityRationCardType": null,
      "ageRationCardType": null,
      "selfServiceRegisteredNo": null,
      "selfServicePinNo": null,
      "selfServicePinNoUpdatedOn": null,
      "customerBranchId": 12,
      "customerBankId": 1,
      "biometricType": null,
      "axisCustIdSentStatus": false,
      "referenceNo": null,
      "enrollmentCheckerStatus": null,
      "enrollmentCheckerRemarks": null,
      "enrollmentCheckerApprover": null,
      "enrollmentCheckerApprovedDate": null,
      "verifiedUserId": null,
      "biometricEnrollment": "NOT-ENABLE",
      "edfDoneAt": "2022-11-09T06:25:37Z",
      "edfCapturedUserId": "process-automation-service",
      "edfCapturedUserName": "Process Automation",
      "termsAndConditionsExplained": null,
      "addressProofNo": "492368691011",
      "currentStage": "Completed",
      "pendingApproval": "N",
      "centreId": 534,
      "leftHandThumpImageId": null,
      "leftHandIndexImageId": null,
      "leftHandMiddleImageId": null,
      "leftHandRingImageId": null,
      "leftHandSmallImageId": null,
      "rightHandThumpImageId": null,
      "rightHandIndexImageId": null,
      "rightHandMiddleImageId": null,
      "rightHandRingImageId": null,
      "rightHandSmallImageId": null,
      "photoImageId": "1934e007-c21e-4f10-bd89-5958ad7ebd6a",
      "houseVerificationPhoto": null,
      "nameInLocalLanguage": null,
      "addressInLocalLanguage": null,
      "authenticationRegisterId": null,
      "customerType": "Individual",
      "enterpriseId": null,
      "addressProofReverseImageId": "feb050ed-5a36-4a31-9daf-efda0707f2f9",
      "identityProofReverseImageId": null,
      "oldCustomerId": "weq2oih2",
      "mobileNumber2": null,
      "landmark": "Mahalingapur",
      "inCurrentAddressSince": null,
      "inCurrentAreaSince": null,
      "ownership": null,
      "branchCode": null,
      "centreName": null,
      "udf29": null,
      "udf30": null,
      "udf31": null,
      "udf32": null,
      "whatsAppMobileNo": null,
      "motherName": null,
      "country": null,
      "area": null,
      "properAndMatchingSignboard": null,
      "bribeOffered": null,
      "shopOrganized": null,
      "isIndustrialArea": null,
      "customerAttitudeToKinara": null,
      "bookKeepingQuality": null,
      "challengingChequeBounce": null,
      "allMachinesAreOperational": null,
      "employeeSatisfaction": null,
      "politicalOrPoliceConnections": null,
      "multipleProducts": null,
      "multipleBuyers": null,
      "seasonalBusiness": null,
      "incomeStability": null,
      "utilisationOfBusinessPremises": null,
      "approachForTheBusinessPremises": null,
      "safetyMeasuresForEmployees": null,
      "childLabours": null,
      "isBusinessEffectingTheEnvironment": null,
      "stockMaterialManagement": null,
      "customerWalkinToBusiness": null,
      "email": null,
      "careOf": null,
      "businessSignboardImage": null,
      "existingLoan": null,
      "distanceFromBranch": null,
      "bankStatementPhoto": null,
      "coApplicantRelationshipWithApplicant": null,
      "partnerCode": null,
      "requestedLoanAmount": null,
      "requestedLoanPurpose": null,
      "weddingDate": null,
      "monthlyRent": null,
      "previousRentDetails": null,
      "vehiclesOwned": null,
      "vehiclesFinanced": null,
      "vehiclesFree": null,
      "localityType": null,
      "accomodationType": null,
      "pekrn": null,
      "ekycDone": false,
      "lenderType": null,
      "source": null,
      "cbRemarks": null,
      "organisation": null,
      "designation": null,
      "personalDiscussionComment": null,
      "fcuStatus": null,
      "fraudContainmentUnit": null,
      "blockingRemarks": null,
      "idenCheckStatus": null,
      "idenCheckDatetime": null,
      "marketTransactionInvolved": null,
      "liabilities": [],
      "miscellaneous": null,
      "udf": {
        "id": 67,
        "version": 0,
        "userDefinedFieldValues": {
          "udf7": "uber",
          "udf8": "1234455555",
          "udf23": "Diploma",
          "udf5": "01bd5275-88bf-44a0-a5c2-def2e719fcf8",
          "udf22": "Monthly"
        },
        "userDefinedDateFieldValues": {}
      },
      "enterprise": null,
      "telecallingDetailsId": null,
      "houseStatus": null,
      "noOfRooms": null,
      "riskProfile": null,
      "residenceWallMake": null,
      "lenderCode": null,
      "cattleDetail": null,
      "totalHouseholdExpenses": null,
      "centreCode": null,
      "externalSystemCode": null,
      "addressProofVerifiedDate": null,
      "addressProofVerifiedUser": null,
      "identityProofVerifiedDate": null,
      "identityProofVerifiedUser": null,
      "createdBy": "divya",
      "createdDate": "2022-05-27T10:19:54Z",
      "lastModifiedBy": "process-automation-service",
      "lastModifiedDate": "2022-11-09T06:25:37Z",
      "enterpriseCustomerRelations": [],
      "familyMembers": [
        {
          "id": 125,
          "version": 0,
          "familyMemberFirstName": "RAGHAVENDRA K M",
          "familyMemberMiddleName": null,
          "familyMemberLastName": null,
          "relationShip": "self",
          "gender": "MALE",
          "dateOfBirth": "1958-10-28",
          "educationStatus": null,
          "mobilePhone": "9080610417",
          "familySequenceId": 137,
          "customerId": 172,
          "enrollmentId": "17201",
          "enrolled": false,
          "enrolledUrnNo": "2205276093390001",
          "dead": false,
          "deathCertificateUploaded": false,
          "deceaseDetailsCaptured": null,
          "contributionToExpenditure": null,
          "maritalStatus": "MARRIED",
          "healthStatus": null,
          "salary": null,
          "anualEducationFee": null,
          "isCoApplicant": null,
          "udfId1": "Testing",
          "udfId2": null,
          "udfId3": null,
          "udfId4": null,
          "udfId5": null,
          "noOfDependents": null,
          "migrantType": null,
          "workExperienceInYears": null,
          "academicBreaks": null,
          "academicBreaksReason": null,
          "udfId6": null,
          "udfId7": null,
          "udfId8": null,
          "udfId9": null,
          "udfId10": null,
          "occupation": "Shop Owner",
          "subOccupation": null,
          "incomes": [
            {
              "id": 63,
              "version": 0,
              "customerId": 172,
              "incomeSource": "Deliveries service",
              "incomeEarned": 400000,
              "frequency": null,
              "familyId": 125,
              "monthsPerYear": null,
              "occupationMasterId": null,
              "workSector": null,
              "occupationType": null,
              "skillLevel": null,
              "averageTimeSpent": null,
              "averageReturn": null,
              "incomeType": null,
              "noOfDaysWorkedInMonth": null,
              "udf1": null,
              "udf2": null,
              "udf3": null,
              "udf4": null,
              "udf5": null
            },
            {
              "id": 64,
              "version": 0,
              "customerId": 172,
              "incomeSource": "Rental Income",
              "incomeEarned": 200000,
              "frequency": null,
              "familyId": 125,
              "monthsPerYear": null,
              "occupationMasterId": null,
              "workSector": null,
              "occupationType": null,
              "skillLevel": null,
              "averageTimeSpent": null,
              "averageReturn": null,
              "incomeType": null,
              "noOfDaysWorkedInMonth": null,
              "udf1": null,
              "udf2": null,
              "udf3": null,
              "udf4": null,
              "udf5": null
            },
            {
              "id": 65,
              "version": 0,
              "customerId": 172,
              "incomeSource": "Agri Income",
              "incomeEarned": 300000,
              "frequency": null,
              "familyId": 125,
              "monthsPerYear": null,
              "occupationMasterId": null,
              "workSector": null,
              "occupationType": null,
              "skillLevel": null,
              "averageTimeSpent": null,
              "averageReturn": null,
              "incomeType": null,
              "noOfDaysWorkedInMonth": null,
              "udf1": null,
              "udf2": null,
              "udf3": null,
              "udf4": null,
              "udf5": null
            }
          ]
        }
      ],
      "additionalKYCs": [],
      "physicalAssets": [],
      "propertyAssets": [],
      "vpaDetails": [],
      "expenditures": [],
      "financialAssets": [],
      "verifications": [
        {
          "id": 224,
          "version": 0,
          "customerId": 172,
          "referenceFirstName": "VIJAYA",
          "referenceMiddleName": null,
          "referenceLastName": null,
          "relationship": "Wife",
          "houseNo": null,
          "houseNoIsVerified": null,
          "selfReportedIncome": null,
          "businessSubSector": null,
          "businessSector": null,
          "businessName": null,
          "mobileNo": "8438346413",
          "customerResponse": null,
          "remarks": null,
          "address": "NO 713 PV KOIL STREET POONAMALLEE HIGH ROADD AMINJIKARAI CHENNAI TAMIL NADU 600029",
          "knownSince": null,
          "opinion": null,
          "financialStatus": null,
          "goodsSold": null,
          "goodsBought": null,
          "paymentTerms": null,
          "modeOfPayment": null,
          "outstandingPayable": null,
          "outstandingReceivable": null,
          "occupation": null,
          "contactable": null,
          "yearsOfExperience": null,
          "drinkingWater": null,
          "toiletFacilityType": null,
          "waterFilter": null,
          "emailId": null,
          "qualityOfHouse": null,
          "typeOfArea": null,
          "noOfRooms": null,
          "separateCookingSpace": null,
          "cookingEnergySource": null,
          "udf1": null,
          "udf2": null,
          "udf3": null,
          "udf4": null,
          "udf5": null
        },
        {
          "id": 225,
          "version": 0,
          "customerId": 172,
          "referenceFirstName": "ARUN GURU",
          "referenceMiddleName": null,
          "referenceLastName": null,
          "relationship": "Brother",
          "houseNo": null,
          "houseNoIsVerified": null,
          "selfReportedIncome": null,
          "businessSubSector": null,
          "businessSector": null,
          "businessName": null,
          "mobileNo": "9791077870",
          "customerResponse": null,
          "remarks": null,
          "address": "NO 713 PV KOIL STREET POONAMALLEE HIGH ROADD AMINJIKARAI CHENNAI TAMIL NADU 600029",
          "knownSince": null,
          "opinion": null,
          "financialStatus": null,
          "goodsSold": null,
          "goodsBought": null,
          "paymentTerms": null,
          "modeOfPayment": null,
          "outstandingPayable": null,
          "outstandingReceivable": null,
          "occupation": null,
          "contactable": null,
          "yearsOfExperience": null,
          "drinkingWater": null,
          "toiletFacilityType": null,
          "waterFilter": null,
          "emailId": null,
          "qualityOfHouse": null,
          "typeOfArea": null,
          "noOfRooms": null,
          "separateCookingSpace": null,
          "cookingEnergySource": null,
          "udf1": null,
          "udf2": null,
          "udf3": null,
          "udf4": null,
          "udf5": null
        }
      ],
      "meFamilyMappings": [],
      "customerBankAccounts": [
        {
          "id": 108,
          "version": 1,
          "customerId": 172,
          "customerBankName": "KARNATAKA BANK LIMITED",
          "customerBankBranchName": "KANAKADASANAGAR",
          "ifscCode": "KARB0000623",
          "accountNumber": "6912937717",
          "accountType": "Savings",
          "isDisbersementAccount": false,
          "customerNameAsInBank": "ajSBDc;abscaj",
          "accountName": null,
          "bankingSince": null,
          "netBankingAvailable": null,
          "bankStatements": [
            {
              "id": 346,
              "version": 0,
              "customerBankAccountId": 108,
              "customerId": 172,
              "startMonth": "2020-05-01",
              "cashDeposits": null,
              "nonCashDeposits": null,
              "totalDeposits": null,
              "totalWithdrawals": null,
              "balanceAsOn15th": null,
              "noOfChequeBounced": null,
              "noOfEmiChequeBounced": null,
              "bankStatementPhoto": null,
              "endMonth": null,
              "openingBalance": null,
              "closingBalance": null,
              "amountOfEmiDeducted": null,
              "averageBankBalance": null,
              "percentageThroughput": null,
              "inwardChequeBounce": null,
              "chequeIssued": null,
              "inwardChequeReturns": null,
              "chequesDeposited": null,
              "outwardChequeReturns": null,
              "outwardChequeBounce": null,
              "udf1": null,
              "udf2": null,
              "udf3": null,
              "udfDate1": null,
              "udfDate2": null,
              "bankStatementPassword": null,
              "statementScanned": false,
              "inputSource": null,
              "bankWithdrawals": null,
              "cashWithdrawals": null,
              "minBalanceCharge": null,
              "lowestMinBalance": null
            },
            {
              "id": 347,
              "version": 0,
              "customerBankAccountId": 108,
              "customerId": 172,
              "startMonth": "2020-06-01",
              "cashDeposits": null,
              "nonCashDeposits": null,
              "totalDeposits": null,
              "totalWithdrawals": null,
              "balanceAsOn15th": null,
              "noOfChequeBounced": null,
              "noOfEmiChequeBounced": null,
              "bankStatementPhoto": null,
              "endMonth": null,
              "openingBalance": null,
              "closingBalance": null,
              "amountOfEmiDeducted": null,
              "averageBankBalance": null,
              "percentageThroughput": null,
              "inwardChequeBounce": null,
              "chequeIssued": null,
              "inwardChequeReturns": null,
              "chequesDeposited": null,
              "outwardChequeReturns": null,
              "outwardChequeBounce": null,
              "udf1": null,
              "udf2": null,
              "udf3": null,
              "udfDate1": null,
              "udfDate2": null,
              "bankStatementPassword": null,
              "statementScanned": false,
              "inputSource": null,
              "bankWithdrawals": null,
              "cashWithdrawals": null,
              "minBalanceCharge": null,
              "lowestMinBalance": null
            },
            {
              "id": 348,
              "version": 0,
              "customerBankAccountId": 108,
              "customerId": 172,
              "startMonth": "2020-07-01",
              "cashDeposits": null,
              "nonCashDeposits": null,
              "totalDeposits": null,
              "totalWithdrawals": null,
              "balanceAsOn15th": null,
              "noOfChequeBounced": null,
              "noOfEmiChequeBounced": null,
              "bankStatementPhoto": null,
              "endMonth": null,
              "openingBalance": null,
              "closingBalance": null,
              "amountOfEmiDeducted": null,
              "averageBankBalance": null,
              "percentageThroughput": null,
              "inwardChequeBounce": null,
              "chequeIssued": null,
              "inwardChequeReturns": null,
              "chequesDeposited": null,
              "outwardChequeReturns": null,
              "outwardChequeBounce": null,
              "udf1": null,
              "udf2": null,
              "udf3": null,
              "udfDate1": null,
              "udfDate2": null,
              "bankStatementPassword": null,
              "statementScanned": false,
              "inputSource": null,
              "bankWithdrawals": null,
              "cashWithdrawals": null,
              "minBalanceCharge": null,
              "lowestMinBalance": null
            },
            {
              "id": 349,
              "version": 0,
              "customerBankAccountId": 108,
              "customerId": 172,
              "startMonth": "2020-08-01",
              "cashDeposits": null,
              "nonCashDeposits": null,
              "totalDeposits": null,
              "totalWithdrawals": null,
              "balanceAsOn15th": null,
              "noOfChequeBounced": null,
              "noOfEmiChequeBounced": null,
              "bankStatementPhoto": null,
              "endMonth": null,
              "openingBalance": null,
              "closingBalance": null,
              "amountOfEmiDeducted": null,
              "averageBankBalance": null,
              "percentageThroughput": null,
              "inwardChequeBounce": null,
              "chequeIssued": null,
              "inwardChequeReturns": null,
              "chequesDeposited": null,
              "outwardChequeReturns": null,
              "outwardChequeBounce": null,
              "udf1": null,
              "udf2": null,
              "udf3": null,
              "udfDate1": null,
              "udfDate2": null,
              "bankStatementPassword": null,
              "statementScanned": false,
              "inputSource": null,
              "bankWithdrawals": null,
              "cashWithdrawals": null,
              "minBalanceCharge": null,
              "lowestMinBalance": null
            },
            {
              "id": 350,
              "version": 0,
              "customerBankAccountId": 108,
              "customerId": 172,
              "startMonth": "2020-09-01",
              "cashDeposits": null,
              "nonCashDeposits": null,
              "totalDeposits": null,
              "totalWithdrawals": null,
              "balanceAsOn15th": null,
              "noOfChequeBounced": null,
              "noOfEmiChequeBounced": null,
              "bankStatementPhoto": null,
              "endMonth": null,
              "openingBalance": null,
              "closingBalance": null,
              "amountOfEmiDeducted": null,
              "averageBankBalance": null,
              "percentageThroughput": null,
              "inwardChequeBounce": null,
              "chequeIssued": null,
              "inwardChequeReturns": null,
              "chequesDeposited": null,
              "outwardChequeReturns": null,
              "outwardChequeBounce": null,
              "udf1": null,
              "udf2": null,
              "udf3": null,
              "udfDate1": null,
              "udfDate2": null,
              "bankStatementPassword": null,
              "statementScanned": false,
              "inputSource": null,
              "bankWithdrawals": null,
              "cashWithdrawals": null,
              "minBalanceCharge": null,
              "lowestMinBalance": null
            },
            {
              "id": 351,
              "version": 0,
              "customerBankAccountId": 108,
              "customerId": 172,
              "startMonth": "2020-10-01",
              "cashDeposits": null,
              "nonCashDeposits": null,
              "totalDeposits": null,
              "totalWithdrawals": null,
              "balanceAsOn15th": null,
              "noOfChequeBounced": null,
              "noOfEmiChequeBounced": null,
              "bankStatementPhoto": null,
              "endMonth": null,
              "openingBalance": null,
              "closingBalance": null,
              "amountOfEmiDeducted": null,
              "averageBankBalance": null,
              "percentageThroughput": null,
              "inwardChequeBounce": null,
              "chequeIssued": null,
              "inwardChequeReturns": null,
              "chequesDeposited": null,
              "outwardChequeReturns": null,
              "outwardChequeBounce": null,
              "udf1": null,
              "udf2": null,
              "udf3": null,
              "udfDate1": null,
              "udfDate2": null,
              "bankStatementPassword": null,
              "statementScanned": false,
              "inputSource": null,
              "bankWithdrawals": null,
              "cashWithdrawals": null,
              "minBalanceCharge": null,
              "lowestMinBalance": null
            }
          ],
          "sanctionedAmount": null,
          "bankStatementDocId": null,
          "confirmedAccountNumber": "6912937717",
          "limit": null,
          "defaultCollectionAccount": null,
          "isTransactionAccount": null,
          "udf1": "35582ffe-d7ee-4104-883a-a5d9f0e896fb",
          "udf2": "78cbdf5f-1a1a-4609-88d2-59dcdc8a88e8",
          "udf3": null,
          "udf4": null,
          "udf5": null,
          "averageBankBalance": null,
          "externalSummaryRequired": false,
          "statementAvailableFrom": null,
          "statementAvailableTo": null
        }
      ],
      "enterpriseRegistrations": [],
      "enterpriseAssets": [],
      "incomeThroughSales": [],
      "otherBusinessIncomes": [],
      "rawMaterialExpenses": [],
      "fixedAssetsMachinaries": [],
      "buyerDetails": [],
      "supplierDetails": [],
      "financialSummaries": [],
      "enterpriseBureauDetails": [],
      "cbCheckList": [],
      "customerPartner": [
        {
          "id": 59,
          "version": 0,
          "customerId": 172,
          "partnerCode": "northernarc",
          "customerPartnerNumber": "5119463424775197"
        }
      ],
      "currentAssets": [],
      "lenderContactDetails": [],
      "enterpriseMonthlySales": [],
      "enterpriseDocuments": [],
      "enterpriseNetworth": [],
      "customerLicenceDetails": [],
      "customerDocuments": [],
      "enterpriseGstFiling": [],
      "enterpriseItrFiling": [],
      "fieldInvestigationDetails": [],
      "enterpriseLegalAndCompliances": [],
      "enterpriseEdcTerminalStatuses": [],
      "enterpriseRegistrationTypeAndNumberList": [],
      "enterpriseDailySales": [],
      "enterpriseProductSales": [],
      "verifiedMobileNumbers": {},
      "driverIncomeMaster": null,
      "highmarkInterfaceId": null,
      "limitId": null,
      "partnerCustomerId": null,
      "riskIndex": null,
      "spiceRiskScore": null,
      "merchantBusinessType": null,
      "loanEligibility": null,
      "loanEligibilityAmount": null,
      "totalLoanCount": null,
      "doj": null,
      "shopName": null,
      "firstLenderPriority": null,
      "secondLenderPriority": null,
      "thirdLenderPriority": null,
      "tenure": null,
      "interestRate": null,
      "interestType": null,
      "processingFee": null,
      "selfie1": null,
      "selfie2": null,
      "monthlyTurnover": null,
      "bureauReport": null,
      "okycVerified": null,
      "duplicateCustomerId": null,
      "cKYC": null,
      "customerPassportFileNo": null
    },
    "processType": null,
    "accountNumber": null,
    "customerIndexStatus": null,
    "currentStage": "Completed"
  },
  "enterpriseDTO": {
    "id": 172,
    "version": 21,
    "enrollmentId": "00002705221549532520",
    "urnNo": "2205276093390001",
    "firstName": "RAGHAVENDRA K M",
    "lastName": "awdawdaw",
    "middleName": "",
    "nickName": null,
    "fatherFirstName": "MANI",
    "fatherLastName": "",
    "fatherMiddleName": "",
    "maritalStatus": "MARRIED",
    "citizenOfIndia": null,
    "employmentStatus": null,
    "landLineNo": null,
    "mobilePhone": "9080610417",
    "stdCode": null,
    "dateOfBirth": "1958-10-28",
    "gender": "MALE",
    "dateOfBirthLong": -352791000000,
    "customerCategory": null,
    "title": "false",
    "spouseFirstName": "undefined",
    "spouseMiddleName": "",
    "spouseLastName": "",
    "spouseDateOfBirth": "1991-05-15",
    "caste": null,
    "religion": null,
    "language": "Hindi",
    "exserviceman": null,
    "villageName": "Mahalingapur(Rural)",
    "occupation1": "Deliveries service",
    "occupation2": "Rental Income",
    "occupation3": "Agri Income",
    "occupation4": null,
    "kgfsName": "Head Office",
    "kgfsBankName": "DvaraMoney",
    "kycFurnishedCopyEnclosed": null,
    "doorNo": "NO 713 PV KOIL STREET POONAMALLEE HIGH ROADD AMINJIKARAI CHENNAI TAMIL NADU 600029",
    "street": "hkghvgjlgv",
    "postOffice": "Aminijikarai POST OFFICE",
    "locality": "Mahalingapur(Rural)",
    "district": "BAGALKOT",
    "state": "KARNATAKA",
    "pincode": 587312,
    "mailSameAsResidence": false,
    "mailingDoorNo": "NO 713 PV KOIL STREET POONAMALLEE HIGH ROADD AMINJIKARAI CHENNAI TAMIL NADU 600029",
    "mailingStreet": "hkghvgjlgv",
    "mailingLocality": "Mahalingapur(Rural)",
    "mailingPostoffice": "Aminijikarai POST OFFICE",
    "mailingDistrict": "BAGALKOT",
    "mailingState": "KARNATAKA",
    "mailingPincode": "587312",
    "addressProof": "Aadhar Card",
    "identityProof": "Pan Card",
    "identityProofNo": "BPTPR9431R",
    "panNo": "BPTPR9431R",
    "yearsOfExperience": null,
    "nameOfRo": "Divya",
    "date": "2022-05-27",
    "place": null,
    "addressProofImageId": "7b698aa6-7e7a-4334-9b81-35774a88738f",
    "identityProofImageId": "d286bb02-8557-449c-9013-16f53fff8ea6",
    "verified": false,
    "parentCustomerId": 0,
    "familyEnrollmentId": null,
    "latestPanStatus": null,
    "latestPanStatusUpdatedOn": null,
    "offlineUploadedOn": null,
    "panCardImageId": null,
    "customerStatus": "ACTIVE",
    "mobileEnrollment": null,
    "mobileEnrollmentId": null,
    "urnGeneratedDate": "2022-05-27T10:19:54Z",
    "bcCustId": "IR0000177",
    "inviteId": null,
    "latitude": null,
    "longitude": null,
    "altitude": null,
    "gpsCaptureDate": null,
    "enrolledAs": "CUSTOMER",
    "blocked": false,
    "blockStatusChangedBy": null,
    "blockStatusChangedAt": null,
    "cifNo": null,
    "sanctionListBlocked": false,
    "addressProofIssueDate": null,
    "addressProofValidUptoDate": null,
    "idProofIssueDate": null,
    "idProofValidUptoDate": null,
    "ageProof": null,
    "ageProofImageId": null,
    "aadhaarNo": "492368691011",
    "eidNumber": null,
    "eidDate": null,
    "addressRationCardType": null,
    "identityRationCardType": null,
    "ageRationCardType": null,
    "selfServiceRegisteredNo": null,
    "selfServicePinNo": null,
    "selfServicePinNoUpdatedOn": null,
    "customerBranchId": 12,
    "customerBankId": 1,
    "biometricType": null,
    "axisCustIdSentStatus": false,
    "referenceNo": null,
    "enrollmentCheckerStatus": null,
    "enrollmentCheckerRemarks": null,
    "enrollmentCheckerApprover": null,
    "enrollmentCheckerApprovedDate": null,
    "verifiedUserId": null,
    "biometricEnrollment": "NOT-ENABLE",
    "edfDoneAt": "2022-11-09T06:25:37Z",
    "edfCapturedUserId": "process-automation-service",
    "edfCapturedUserName": "Process Automation",
    "termsAndConditionsExplained": null,
    "addressProofNo": "492368691011",
    "currentStage": "Completed",
    "pendingApproval": "N",
    "centreId": 534,
    "leftHandThumpImageId": null,
    "leftHandIndexImageId": null,
    "leftHandMiddleImageId": null,
    "leftHandRingImageId": null,
    "leftHandSmallImageId": null,
    "rightHandThumpImageId": null,
    "rightHandIndexImageId": null,
    "rightHandMiddleImageId": null,
    "rightHandRingImageId": null,
    "rightHandSmallImageId": null,
    "photoImageId": "1934e007-c21e-4f10-bd89-5958ad7ebd6a",
    "houseVerificationPhoto": null,
    "nameInLocalLanguage": null,
    "addressInLocalLanguage": null,
    "authenticationRegisterId": null,
    "customerType": "Individual",
    "enterpriseId": null,
    "addressProofReverseImageId": "feb050ed-5a36-4a31-9daf-efda0707f2f9",
    "identityProofReverseImageId": null,
    "oldCustomerId": "weq2oih2",
    "mobileNumber2": null,
    "landmark": "Mahalingapur",
    "inCurrentAddressSince": null,
    "inCurrentAreaSince": null,
    "ownership": null,
    "branchCode": null,
    "centreName": null,
    "udf29": null,
    "udf30": null,
    "udf31": null,
    "udf32": null,
    "whatsAppMobileNo": null,
    "motherName": null,
    "country": null,
    "area": null,
    "properAndMatchingSignboard": null,
    "bribeOffered": null,
    "shopOrganized": null,
    "isIndustrialArea": null,
    "customerAttitudeToKinara": null,
    "bookKeepingQuality": null,
    "challengingChequeBounce": null,
    "allMachinesAreOperational": null,
    "employeeSatisfaction": null,
    "politicalOrPoliceConnections": null,
    "multipleProducts": null,
    "multipleBuyers": null,
    "seasonalBusiness": null,
    "incomeStability": null,
    "utilisationOfBusinessPremises": null,
    "approachForTheBusinessPremises": null,
    "safetyMeasuresForEmployees": null,
    "childLabours": null,
    "isBusinessEffectingTheEnvironment": null,
    "stockMaterialManagement": null,
    "customerWalkinToBusiness": null,
    "email": null,
    "careOf": null,
    "businessSignboardImage": null,
    "existingLoan": null,
    "distanceFromBranch": null,
    "bankStatementPhoto": null,
    "coApplicantRelationshipWithApplicant": null,
    "partnerCode": null,
    "requestedLoanAmount": null,
    "requestedLoanPurpose": null,
    "weddingDate": null,
    "monthlyRent": null,
    "previousRentDetails": null,
    "vehiclesOwned": null,
    "vehiclesFinanced": null,
    "vehiclesFree": null,
    "localityType": null,
    "accomodationType": null,
    "pekrn": null,
    "ekycDone": false,
    "lenderType": null,
    "source": null,
    "cbRemarks": null,
    "organisation": null,
    "designation": null,
    "personalDiscussionComment": null,
    "fcuStatus": null,
    "fraudContainmentUnit": null,
    "blockingRemarks": null,
    "idenCheckStatus": null,
    "idenCheckDatetime": null,
    "marketTransactionInvolved": null,
    "liabilities": [],
    "miscellaneous": null,
    "udf": {
      "id": 67,
      "version": 0,
      "userDefinedFieldValues": {
        "udf7": "uber",
        "udf8": "1234455555",
        "udf23": "Diploma",
        "udf5": "01bd5275-88bf-44a0-a5c2-def2e719fcf8",
        "udf22": "Monthly"
      },
      "userDefinedDateFieldValues": {}
    },
    "enterprise": null,
    "telecallingDetailsId": null,
    "houseStatus": null,
    "noOfRooms": null,
    "riskProfile": null,
    "residenceWallMake": null,
    "lenderCode": null,
    "cattleDetail": null,
    "totalHouseholdExpenses": null,
    "centreCode": null,
    "externalSystemCode": null,
    "addressProofVerifiedDate": null,
    "addressProofVerifiedUser": null,
    "identityProofVerifiedDate": null,
    "identityProofVerifiedUser": null,
    "createdBy": "divya",
    "createdDate": "2022-05-27T10:19:54Z",
    "lastModifiedBy": "process-automation-service",
    "lastModifiedDate": "2022-11-09T06:25:37Z",
    "enterpriseCustomerRelations": [],
    "familyMembers": [
      {
        "id": 125,
        "version": 0,
        "familyMemberFirstName": "RAGHAVENDRA K M",
        "familyMemberMiddleName": null,
        "familyMemberLastName": null,
        "relationShip": "self",
        "gender": "MALE",
        "dateOfBirth": "1958-10-28",
        "educationStatus": null,
        "mobilePhone": "9080610417",
        "familySequenceId": 137,
        "customerId": 172,
        "enrollmentId": "17201",
        "enrolled": false,
        "enrolledUrnNo": "2205276093390001",
        "dead": false,
        "deathCertificateUploaded": false,
        "deceaseDetailsCaptured": null,
        "contributionToExpenditure": null,
        "maritalStatus": "MARRIED",
        "healthStatus": null,
        "salary": null,
        "anualEducationFee": null,
        "isCoApplicant": null,
        "udfId1": "Testing",
        "udfId2": null,
        "udfId3": null,
        "udfId4": null,
        "udfId5": null,
        "noOfDependents": null,
        "migrantType": null,
        "workExperienceInYears": null,
        "academicBreaks": null,
        "academicBreaksReason": null,
        "udfId6": null,
        "udfId7": null,
        "udfId8": null,
        "udfId9": null,
        "udfId10": null,
        "occupation": "Shop Owner",
        "subOccupation": null,
        "incomes": [
          {
            "id": 63,
            "version": 0,
            "customerId": 172,
            "incomeSource": "Deliveries service",
            "incomeEarned": 400000,
            "frequency": null,
            "familyId": 125,
            "monthsPerYear": null,
            "occupationMasterId": null,
            "workSector": null,
            "occupationType": null,
            "skillLevel": null,
            "averageTimeSpent": null,
            "averageReturn": null,
            "incomeType": null,
            "noOfDaysWorkedInMonth": null,
            "udf1": null,
            "udf2": null,
            "udf3": null,
            "udf4": null,
            "udf5": null
          },
          {
            "id": 64,
            "version": 0,
            "customerId": 172,
            "incomeSource": "Rental Income",
            "incomeEarned": 200000,
            "frequency": null,
            "familyId": 125,
            "monthsPerYear": null,
            "occupationMasterId": null,
            "workSector": null,
            "occupationType": null,
            "skillLevel": null,
            "averageTimeSpent": null,
            "averageReturn": null,
            "incomeType": null,
            "noOfDaysWorkedInMonth": null,
            "udf1": null,
            "udf2": null,
            "udf3": null,
            "udf4": null,
            "udf5": null
          },
          {
            "id": 65,
            "version": 0,
            "customerId": 172,
            "incomeSource": "Agri Income",
            "incomeEarned": 300000,
            "frequency": null,
            "familyId": 125,
            "monthsPerYear": null,
            "occupationMasterId": null,
            "workSector": null,
            "occupationType": null,
            "skillLevel": null,
            "averageTimeSpent": null,
            "averageReturn": null,
            "incomeType": null,
            "noOfDaysWorkedInMonth": null,
            "udf1": null,
            "udf2": null,
            "udf3": null,
            "udf4": null,
            "udf5": null
          }
        ]
      }
    ],
    "additionalKYCs": [],
    "physicalAssets": [],
    "propertyAssets": [],
    "vpaDetails": [],
    "expenditures": [],
    "financialAssets": [],
    "verifications": [
      {
        "id": 224,
        "version": 0,
        "customerId": 172,
        "referenceFirstName": "VIJAYA",
        "referenceMiddleName": null,
        "referenceLastName": null,
        "relationship": "Wife",
        "houseNo": null,
        "houseNoIsVerified": null,
        "selfReportedIncome": null,
        "businessSubSector": null,
        "businessSector": null,
        "businessName": null,
        "mobileNo": "8438346413",
        "customerResponse": null,
        "remarks": null,
        "address": "NO 713 PV KOIL STREET POONAMALLEE HIGH ROADD AMINJIKARAI CHENNAI TAMIL NADU 600029",
        "knownSince": null,
        "opinion": null,
        "financialStatus": null,
        "goodsSold": null,
        "goodsBought": null,
        "paymentTerms": null,
        "modeOfPayment": null,
        "outstandingPayable": null,
        "outstandingReceivable": null,
        "occupation": null,
        "contactable": null,
        "yearsOfExperience": null,
        "drinkingWater": null,
        "toiletFacilityType": null,
        "waterFilter": null,
        "emailId": null,
        "qualityOfHouse": null,
        "typeOfArea": null,
        "noOfRooms": null,
        "separateCookingSpace": null,
        "cookingEnergySource": null,
        "udf1": null,
        "udf2": null,
        "udf3": null,
        "udf4": null,
        "udf5": null
      },
      {
        "id": 225,
        "version": 0,
        "customerId": 172,
        "referenceFirstName": "ARUN GURU",
        "referenceMiddleName": null,
        "referenceLastName": null,
        "relationship": "Brother",
        "houseNo": null,
        "houseNoIsVerified": null,
        "selfReportedIncome": null,
        "businessSubSector": null,
        "businessSector": null,
        "businessName": null,
        "mobileNo": "9791077870",
        "customerResponse": null,
        "remarks": null,
        "address": "NO 713 PV KOIL STREET POONAMALLEE HIGH ROADD AMINJIKARAI CHENNAI TAMIL NADU 600029",
        "knownSince": null,
        "opinion": null,
        "financialStatus": null,
        "goodsSold": null,
        "goodsBought": null,
        "paymentTerms": null,
        "modeOfPayment": null,
        "outstandingPayable": null,
        "outstandingReceivable": null,
        "occupation": null,
        "contactable": null,
        "yearsOfExperience": null,
        "drinkingWater": null,
        "toiletFacilityType": null,
        "waterFilter": null,
        "emailId": null,
        "qualityOfHouse": null,
        "typeOfArea": null,
        "noOfRooms": null,
        "separateCookingSpace": null,
        "cookingEnergySource": null,
        "udf1": null,
        "udf2": null,
        "udf3": null,
        "udf4": null,
        "udf5": null
      }
    ],
    "meFamilyMappings": [],
    "customerBankAccounts": [
      {
        "id": 108,
        "version": 1,
        "customerId": 172,
        "customerBankName": "KARNATAKA BANK LIMITED",
        "customerBankBranchName": "KANAKADASANAGAR",
        "ifscCode": "KARB0000623",
        "accountNumber": "6912937717",
        "accountType": "Savings",
        "isDisbersementAccount": false,
        "customerNameAsInBank": "ajSBDc;abscaj",
        "accountName": null,
        "bankingSince": null,
        "netBankingAvailable": null,
        "bankStatements": [
          {
            "id": 346,
            "version": 0,
            "customerBankAccountId": 108,
            "customerId": 172,
            "startMonth": "2020-05-01",
            "cashDeposits": null,
            "nonCashDeposits": null,
            "totalDeposits": null,
            "totalWithdrawals": null,
            "balanceAsOn15th": null,
            "noOfChequeBounced": null,
            "noOfEmiChequeBounced": null,
            "bankStatementPhoto": null,
            "endMonth": null,
            "openingBalance": null,
            "closingBalance": null,
            "amountOfEmiDeducted": null,
            "averageBankBalance": null,
            "percentageThroughput": null,
            "inwardChequeBounce": null,
            "chequeIssued": null,
            "inwardChequeReturns": null,
            "chequesDeposited": null,
            "outwardChequeReturns": null,
            "outwardChequeBounce": null,
            "udf1": null,
            "udf2": null,
            "udf3": null,
            "udfDate1": null,
            "udfDate2": null,
            "bankStatementPassword": null,
            "statementScanned": false,
            "inputSource": null,
            "bankWithdrawals": null,
            "cashWithdrawals": null,
            "minBalanceCharge": null,
            "lowestMinBalance": null
          },
          {
            "id": 347,
            "version": 0,
            "customerBankAccountId": 108,
            "customerId": 172,
            "startMonth": "2020-06-01",
            "cashDeposits": null,
            "nonCashDeposits": null,
            "totalDeposits": null,
            "totalWithdrawals": null,
            "balanceAsOn15th": null,
            "noOfChequeBounced": null,
            "noOfEmiChequeBounced": null,
            "bankStatementPhoto": null,
            "endMonth": null,
            "openingBalance": null,
            "closingBalance": null,
            "amountOfEmiDeducted": null,
            "averageBankBalance": null,
            "percentageThroughput": null,
            "inwardChequeBounce": null,
            "chequeIssued": null,
            "inwardChequeReturns": null,
            "chequesDeposited": null,
            "outwardChequeReturns": null,
            "outwardChequeBounce": null,
            "udf1": null,
            "udf2": null,
            "udf3": null,
            "udfDate1": null,
            "udfDate2": null,
            "bankStatementPassword": null,
            "statementScanned": false,
            "inputSource": null,
            "bankWithdrawals": null,
            "cashWithdrawals": null,
            "minBalanceCharge": null,
            "lowestMinBalance": null
          },
          {
            "id": 348,
            "version": 0,
            "customerBankAccountId": 108,
            "customerId": 172,
            "startMonth": "2020-07-01",
            "cashDeposits": null,
            "nonCashDeposits": null,
            "totalDeposits": null,
            "totalWithdrawals": null,
            "balanceAsOn15th": null,
            "noOfChequeBounced": null,
            "noOfEmiChequeBounced": null,
            "bankStatementPhoto": null,
            "endMonth": null,
            "openingBalance": null,
            "closingBalance": null,
            "amountOfEmiDeducted": null,
            "averageBankBalance": null,
            "percentageThroughput": null,
            "inwardChequeBounce": null,
            "chequeIssued": null,
            "inwardChequeReturns": null,
            "chequesDeposited": null,
            "outwardChequeReturns": null,
            "outwardChequeBounce": null,
            "udf1": null,
            "udf2": null,
            "udf3": null,
            "udfDate1": null,
            "udfDate2": null,
            "bankStatementPassword": null,
            "statementScanned": false,
            "inputSource": null,
            "bankWithdrawals": null,
            "cashWithdrawals": null,
            "minBalanceCharge": null,
            "lowestMinBalance": null
          },
          {
            "id": 349,
            "version": 0,
            "customerBankAccountId": 108,
            "customerId": 172,
            "startMonth": "2020-08-01",
            "cashDeposits": null,
            "nonCashDeposits": null,
            "totalDeposits": null,
            "totalWithdrawals": null,
            "balanceAsOn15th": null,
            "noOfChequeBounced": null,
            "noOfEmiChequeBounced": null,
            "bankStatementPhoto": null,
            "endMonth": null,
            "openingBalance": null,
            "closingBalance": null,
            "amountOfEmiDeducted": null,
            "averageBankBalance": null,
            "percentageThroughput": null,
            "inwardChequeBounce": null,
            "chequeIssued": null,
            "inwardChequeReturns": null,
            "chequesDeposited": null,
            "outwardChequeReturns": null,
            "outwardChequeBounce": null,
            "udf1": null,
            "udf2": null,
            "udf3": null,
            "udfDate1": null,
            "udfDate2": null,
            "bankStatementPassword": null,
            "statementScanned": false,
            "inputSource": null,
            "bankWithdrawals": null,
            "cashWithdrawals": null,
            "minBalanceCharge": null,
            "lowestMinBalance": null
          },
          {
            "id": 350,
            "version": 0,
            "customerBankAccountId": 108,
            "customerId": 172,
            "startMonth": "2020-09-01",
            "cashDeposits": null,
            "nonCashDeposits": null,
            "totalDeposits": null,
            "totalWithdrawals": null,
            "balanceAsOn15th": null,
            "noOfChequeBounced": null,
            "noOfEmiChequeBounced": null,
            "bankStatementPhoto": null,
            "endMonth": null,
            "openingBalance": null,
            "closingBalance": null,
            "amountOfEmiDeducted": null,
            "averageBankBalance": null,
            "percentageThroughput": null,
            "inwardChequeBounce": null,
            "chequeIssued": null,
            "inwardChequeReturns": null,
            "chequesDeposited": null,
            "outwardChequeReturns": null,
            "outwardChequeBounce": null,
            "udf1": null,
            "udf2": null,
            "udf3": null,
            "udfDate1": null,
            "udfDate2": null,
            "bankStatementPassword": null,
            "statementScanned": false,
            "inputSource": null,
            "bankWithdrawals": null,
            "cashWithdrawals": null,
            "minBalanceCharge": null,
            "lowestMinBalance": null
          },
          {
            "id": 351,
            "version": 0,
            "customerBankAccountId": 108,
            "customerId": 172,
            "startMonth": "2020-10-01",
            "cashDeposits": null,
            "nonCashDeposits": null,
            "totalDeposits": null,
            "totalWithdrawals": null,
            "balanceAsOn15th": null,
            "noOfChequeBounced": null,
            "noOfEmiChequeBounced": null,
            "bankStatementPhoto": null,
            "endMonth": null,
            "openingBalance": null,
            "closingBalance": null,
            "amountOfEmiDeducted": null,
            "averageBankBalance": null,
            "percentageThroughput": null,
            "inwardChequeBounce": null,
            "chequeIssued": null,
            "inwardChequeReturns": null,
            "chequesDeposited": null,
            "outwardChequeReturns": null,
            "outwardChequeBounce": null,
            "udf1": null,
            "udf2": null,
            "udf3": null,
            "udfDate1": null,
            "udfDate2": null,
            "bankStatementPassword": null,
            "statementScanned": false,
            "inputSource": null,
            "bankWithdrawals": null,
            "cashWithdrawals": null,
            "minBalanceCharge": null,
            "lowestMinBalance": null
          }
        ],
        "sanctionedAmount": null,
        "bankStatementDocId": null,
        "confirmedAccountNumber": "6912937717",
        "limit": null,
        "defaultCollectionAccount": null,
        "isTransactionAccount": null,
        "udf1": "35582ffe-d7ee-4104-883a-a5d9f0e896fb",
        "udf2": "78cbdf5f-1a1a-4609-88d2-59dcdc8a88e8",
        "udf3": null,
        "udf4": null,
        "udf5": null,
        "averageBankBalance": null,
        "externalSummaryRequired": false,
        "statementAvailableFrom": null,
        "statementAvailableTo": null
      }
    ],
    "enterpriseRegistrations": [],
    "enterpriseAssets": [],
    "incomeThroughSales": [],
    "otherBusinessIncomes": [],
    "rawMaterialExpenses": [],
    "fixedAssetsMachinaries": [],
    "buyerDetails": [],
    "supplierDetails": [],
    "financialSummaries": [],
    "enterpriseBureauDetails": [],
    "cbCheckList": [],
    "customerPartner": [
      {
        "id": 59,
        "version": 0,
        "customerId": 172,
        "partnerCode": "northernarc",
        "customerPartnerNumber": "5119463424775197"
      }
    ],
    "currentAssets": [],
    "lenderContactDetails": [],
    "enterpriseMonthlySales": [],
    "enterpriseDocuments": [],
    "enterpriseNetworth": [],
    "customerLicenceDetails": [],
    "customerDocuments": [],
    "enterpriseGstFiling": [],
    "enterpriseItrFiling": [],
    "fieldInvestigationDetails": [],
    "enterpriseLegalAndCompliances": [],
    "enterpriseEdcTerminalStatuses": [],
    "enterpriseRegistrationTypeAndNumberList": [],
    "enterpriseDailySales": [],
    "enterpriseProductSales": [],
    "verifiedMobileNumbers": {},
    "driverIncomeMaster": null,
    "highmarkInterfaceId": null,
    "limitId": null,
    "partnerCustomerId": null,
    "riskIndex": null,
    "spiceRiskScore": null,
    "merchantBusinessType": null,
    "loanEligibility": null,
    "loanEligibilityAmount": null,
    "totalLoanCount": null,
    "doj": null,
    "shopName": null,
    "firstLenderPriority": null,
    "secondLenderPriority": null,
    "thirdLenderPriority": null,
    "tenure": null,
    "interestRate": null,
    "interestType": null,
    "processingFee": null,
    "selfie1": null,
    "selfie2": null,
    "monthlyTurnover": null,
    "bureauReport": null,
    "okycVerified": null,
    "duplicateCustomerId": null,
    "cKYC": null,
    "customerPassportFileNo": null
  },
  "partnerHandoffIntegration": null,
  "outGoingRetryRequired": null,
  "partnerHandoffInterface": null,
  "bureauData": [],
  "repaymentSchedule": null,
  "kycData": null
}